{"Berenice":["35.484","23.946"],"Beni Mazar":["30.810","28.490"],"Samalut":["30.710","28.300"],"El Mansura":["31.380","31.050"],"Mallawi":["30.840","27.730"],"El Minya":["30.750","28.090"],"Siwa":["25.517","29.200"],"Matruh":["27.230","31.350"],"Qena":["32.720","26.151"],"Salum":["25.150","31.567"],"El Daba":["28.433","31.034"],"El Faiyum":["30.840","29.310"],"Asyut":["31.180","27.190"],"Bur Safaga":["33.933","26.734"],"El Alamein":["28.950","30.817"],"Kom Ombo":["32.950","24.470"],"El Giza":["31.190","30.010"],"Isna":["32.550","25.290"],"El Kharga":["30.550","25.440"],"Qasr Farafra":["27.967","27.067"],"Girga":["31.880","26.330"],"El Qasr":["28.883","25.700"],"Hurghada":["33.830","27.230"],"Sohag":["31.700","26.550"],"El Tur":["33.615","28.239"],"Bur Said":["32.290","31.260"],"Tanta":["31.000","30.790"],"Ismailia":["32.260","30.590"],"Suez":["32.550","30.005"],"Beni Suef":["31.090","29.080"],"Aswan":["32.899","24.087"],"Cairo":["31.250","30.050"],"Dumyat":["31.820","31.420"],"Zagazig":["31.517","30.583"],"Alexandria":["29.950","31.200"],"Shibin el Kom":["30.900","30.592"],"El Arish":["33.801","31.125"],"Damanhur":["30.470","31.050"],"Luxor":["32.650","25.700"],"Rashid":["30.390","31.460"],"Kafr el Sheikh":["30.936","31.109"],"Benha":["31.183","30.467"]}